SSparseMatrix/SSparseMatrix.py
SSparseMatrix/__init__.py
ssparsematrix-0.3.5.dist-info/licenses/LICENSE
ssparsematrix-0.3.5.dist-info/METADATA
ssparsematrix-0.3.5.dist-info/WHEEL
ssparsematrix-0.3.5.dist-info/top_level.txt
ssparsematrix-0.3.5.dist-info/RECORD
