Metadata-Version: 2.4
Name: SSparseMatrix
Version: 0.3.5
Summary: SSparseMatrix package based on SciPy sparse matrices.
Home-page: https://github.com/antononcube/Python-packages/tree/main/SSparseMatrix
Author: Anton Antonov
Author-email: antononcube@posteo.net
Keywords: sparse,matrix,r,s,s-plus,linear algebra,linear,algebra,row names,column names,named rows,named columns
Classifier: Intended Audience :: Science/Research
Classifier: Intended Audience :: Developers
Classifier: Programming Language :: Python :: 3
Classifier: License :: OSI Approved :: BSD License
Classifier: Intended Audience :: Science/Research
Classifier: Intended Audience :: Developers
Classifier: Operating System :: OS Independent
Requires-Python: >=3.7
License-File: LICENSE
Requires-Dist: numpy
Requires-Dist: scipy
Dynamic: author
Dynamic: author-email
Dynamic: classifier
Dynamic: description
Dynamic: description-content-type
Dynamic: home-page
Dynamic: keywords
Dynamic: license-file
Dynamic: requires-dist
Dynamic: requires-python
Dynamic: summary
